ae/pythonanywhere.py
ae_pythonanywhere-0.3.2.dist-info/licenses/LICENSE.md
ae_pythonanywhere-0.3.2.dist-info/METADATA
ae_pythonanywhere-0.3.2.dist-info/WHEEL
ae_pythonanywhere-0.3.2.dist-info/top_level.txt
ae_pythonanywhere-0.3.2.dist-info/zip-safe
ae_pythonanywhere-0.3.2.dist-info/RECORD
